flask_sugar/__init__.py
flask_sugar/app.py
flask_sugar/blueprints.py
flask_sugar/constans.py
flask_sugar/datastructures.py
flask_sugar/errorhandlers.py
flask_sugar/exceptions.py
flask_sugar/openapi.py
flask_sugar/param_functions.py
flask_sugar/params.py
flask_sugar/templates.py
flask_sugar/utils.py
flask_sugar/view.py
flask_sugar-0.0.20.dist-info/LICENSE
flask_sugar-0.0.20.dist-info/METADATA
flask_sugar-0.0.20.dist-info/WHEEL
flask_sugar-0.0.20.dist-info/top_level.txt
flask_sugar-0.0.20.dist-info/RECORD
