Metadata-Version: 2.1
Name: flask-sugar
Version: 0.0.20
Summary: Flask Sugar is a web framework for building APIs with Flask, Pydantic and Python 3.6+ type hints.
Home-page: https://github.com/shangsky/flask-sugar
Author: shangsky
Author-email: t_c_y@outlook.com
Maintainer: shangsky
Maintainer-email: t_c_y@outlook.com
License: MIT
Platform: all
Classifier: Development Status :: 4 - Beta
Classifier: Operating System :: OS Independent
Classifier: Intended Audience :: Developers
Classifier: License :: OSI Approved :: MIT License
Classifier: Programming Language :: Python :: 3.6
Classifier: Programming Language :: Python :: 3.7
Classifier: Programming Language :: Python :: 3.8
Classifier: Programming Language :: Python :: 3.9
Classifier: Topic :: Software Development :: Libraries
Requires-Python: >=3.6
Requires-Dist: flask (>=2.0)
Requires-Dist: pydantic (<2.0.0,>=1.8)
